nospace/nospace.py
nospace/setup_test_directory.py
nospace-0.1.1.dist-info/entry_points.txt
nospace-0.1.1.dist-info/LICENSE
nospace-0.1.1.dist-info/WHEEL
nospace-0.1.1.dist-info/METADATA
nospace-0.1.1.dist-info/RECORD
