Metadata-Version: 2.1
Name: nospace
Version: 0.1.1
Summary: recursively rename files and folders to remove spaces and format with optional flags
Home-page: https://github.com/yenaras/nospace
License: MIT
Keywords: cli,spaces,format
Author: yenaras
Author-email: brandon82890@gmail.com
Requires-Python: >=3.10,<4.0
Classifier: License :: OSI Approved :: MIT License
Classifier: Programming Language :: Python :: 3
Classifier: Programming Language :: Python :: 3.10
Project-URL: Repository, https://github.com/yenaras/nospace
